febhd_clustering/__init__.py
febhd_clustering/encoder.py
febhd_clustering/febhd.py
febhd_clustering-0.1.0.dist-info/WHEEL
febhd_clustering-0.1.0.dist-info/METADATA
febhd_clustering-0.1.0.dist-info/RECORD
