Metadata-Version: 2.1
Name: febhd-clustering
Version: 0.1.0
Summary: Smart Hyperdimensional Clustering algorithm: FebHD
Home-page: https://gitlab.com/biaslab/hd-clustering
License: MIT
Author: alehd
Author-email: ale.hdz333@ciencias.unam.mx
Requires-Python: >=3.8,<4.0
Classifier: License :: OSI Approved :: MIT License
Classifier: Programming Language :: Python :: 3
Classifier: Programming Language :: Python :: 3.8
Classifier: Programming Language :: Python :: 3.9
Requires-Dist: torch (>=1.7.1,<2.0.0)
Project-URL: Repository, https://gitlab.com/biaslab/hd-clustering
